sdao/__init__.py
sdao/dao.py
sdao/mariadb/__init__.py
sdao/mariadb/cnn.py
sdao/mariadb/sqlbuilder.py
sdao/mssql/__init__.py
sdao/mssql/cnn.py
sdao/mssql/sqlbuilder.py
sdao/mysql/__init__.py
sdao/mysql/cnn.py
sdao/mysql/sqlbuilder.py
sdao/sqlite/__init__.py
sdao/sqlite/cnn.py
sdao/sqlite/sqlbuilder.py
sdao-1.2.3.dist-info/licenses/LICENSE
sdao-1.2.3.dist-info/METADATA
sdao-1.2.3.dist-info/WHEEL
sdao-1.2.3.dist-info/top_level.txt
sdao-1.2.3.dist-info/RECORD
