Metadata-Version: 2.4
Name: sdao
Version: 1.2.3
Summary: A DAO (Data Access Object) library for Python
Author: Gabriel Valentoni Guelfi
Author-email: Gabriel Valentoni Guelfi <gabriel.valguelfi@gmail.com>
License: MIT License 
Requires-Python: >=3.7
License-File: LICENSE
Provides-Extra: mysql
Requires-Dist: mysql-connector-python; extra == "mysql"
Provides-Extra: mariadb
Requires-Dist: mariadb; extra == "mariadb"
Provides-Extra: mssql
Requires-Dist: pyodbc; extra == "mssql"
Dynamic: author
Dynamic: license-file
Dynamic: requires-python
